thread/rf/regfile.v
module registerFile
(
    input wire clk,
    input wire rst,
    input wire [3:0] rs0,
    input wire [3:0] rs1,
    input wire [27:0] data_in,
    input wire [3:0] dest_sel,
    input wire wen,
    output wire [27:0] dout0,
    output wire [27:0] dout1
);
    // Register file with 16 registers (28 bits each)
    reg [27:0] rf [1:15];  // Only registers 1-15 are stored
    integer i;

    // Register 0 is hardwired to zero
    assign dout0 = (rs0 == 4'b0) ? 28'b0 : rf[rs0];
    assign dout1 = (rs1 == 4'b0) ? 28'b0 : rf[rs1];

    always @(negedge clk or posedge rst) begin
        if (rst) begin
            for (i = 1; i < 16; i = i + 1) begin
                rf[i] <= 28'b0;
            end
        end else if (wen) begin
            rf[dest_sel] <= data_in;
        end
    end
endmodule

thread/rf/regtest.v
`timescale 1ns / 1ps

module registerFile_tb;
    // Inputs
    reg clk;
    reg rst;
    reg [3:0] rs0;
    reg [3:0] rs1;
    reg [27:0] data_in;
    reg [3:0] dest_sel;
    reg wen;

    // Outputs
    wire [27:0] dout0;
    wire [27:0] dout1;

    // Instantiate the Unit Under Test (UUT)
    registerFile uut (
        .clk(clk),
        .rst(rst),
        .rs0(rs0),
        .rs1(rs1),
        .data_in(data_in),
        .dest_sel(dest_sel),
        .wen(wen),
        .dout0(dout0),
        .dout1(dout1)
    );

    // Clock generation: 10ns period
    initial begin
        clk = 0;
        forever #1.5 clk = ~clk;
    end

    initial begin
        $dumpfile("registerFile.vcd");
        $dumpvars(0, registerFile_tb);

        // Test 1: Reset clears all registers to zero
        rst = 1;
        wen = 0;
        rs0 = 4'd0; rs1 = 4'd1;
        #3;
        rst = 0;
        #4.5;
        if (dout0 !== 28'd0 || dout1 !== 28'd0) begin
            $display("[FAIL] Reset did not clear registers: dout0=%h dout1=%h", dout0, dout1);
        end else begin
            $display("[PASS] Reset cleared registers");
        end

        // Test 2: Write to R0 (dest_sel=0) should write zero regardless of data_in
        data_in = 28'hABCDE;
        dest_sel = 4'd0;
        wen = 1;
        #3;
        wen = 0;
        rs0 = 4'd0; rs1 = 4'd0;
        #3;
        if (dout0 !== 28'd0) begin
            $display("[FAIL] Write to R0 should remain zero: dout0=%h", dout0);
        end else begin
            $display("[PASS] R0 write-protected");
        end

        // Test 3: Write and read from multiple registers
        // Write 0x1234567 to R5
        data_in = 28'h1234567;
        dest_sel = 4'd5;
        wen = 1;
        #3;
        wen = 0;
        rs0 = 4'd5; rs1 = 4'd0;
        #3;
        if (dout0 !== 28'h1234567 || dout1 !== 28'd0) begin
            $display("[FAIL] Write/Read mismatch: dout0=%h dout1=%h", dout0, dout1);
        end else begin
            $display("[PASS] Write/read R5 and R0");
        end

        // Test 4: Overwrite a register
        data_in = 28'h0FEDCBA;
        dest_sel = 4'd5;
        wen = 1;
        #3;
        wen = 0;
        rs0 = 4'd5; rs1 = 4'd5;
        #3;
        if (dout0 !== 28'h0FEDCBA || dout1 !== 28'h0FEDCBA) begin
            $display("[FAIL] Overwrite failed: dout0=%h dout1=%h", dout0, dout1);
        end else begin
            $display("[PASS] Overwrite register");
        end
        $display("All tests completed.");
        $finish;
    end
endmodule

thread/rf/registerFile.vcd
$date
	Tue May 20 20:05:29 2025
$end
$version
	Icarus Verilog
$end
$timescale
	1ps
$end
$scope module registerFile_tb $end
$var wire 28 ! dout1 [27:0] $end
$var wire 28 " dout0 [27:0] $end
$var reg 1 # clk $end
$var reg 28 $ data_in [27:0] $end
$var reg 4 % dest_sel [3:0] $end
$var reg 4 & rs0 [3:0] $end
$var reg 4 ' rs1 [3:0] $end
$var reg 1 ( rst $end
$var reg 1 ) wen $end
$scope module uut $end
$var wire 1 # clk $end
$var wire 28 * data_in [27:0] $end
$var wire 4 + dest_sel [3:0] $end
$var wire 4 , rs0 [3:0] $end
$var wire 4 - rs1 [3:0] $end
$var wire 1 ( rst $end
$var wire 1 ) wen $end
$var wire 28 . dout1 [27:0] $end
$var wire 28 / dout0 [27:0] $end
$var integer 32 0 i [31:0] $end
$upscope $end
$upscope $end
$enddefinitions $end
$comment Show the parameter values. $end
$dumpall
$end
#0
$dumpvars
b10000 0
b0 /
b0 .
b1 -
b0 ,
bx +
bx *
0)
1(
b1 '
b0 &
bx %
bx $
0#
b0 "
b0 !
$end
#1500
1#
#3000
0#
0(
#4500
1#
#6000
0#
#7500
1#
1)
b0 %
b0 +
b10101011110011011110 $
b10101011110011011110 *
#9000
0#
#10500
1#
b0 '
b0 -
0)
#12000
0#
#13500
1#
1)
b101 %
b101 +
b1001000110100010101100111 $
b1001000110100010101100111 *
#15000
0#
#16500
b1001000110100010101100111 "
b1001000110100010101100111 /
1#
b101 &
b101 ,
0)
#18000
0#
#19500
1#
1)
b111111101101110010111010 $
b111111101101110010111010 *
#21000
b111111101101110010111010 "
b111111101101110010111010 /
0#
#22500
b111111101101110010111010 !
b111111101101110010111010 .
1#
b101 '
b101 -
0)
